PyL3dMDTest/PyL3dMD.py
PyL3dMDTest/__init__.py
PyL3dMDTest/cpsa.py
PyL3dMDTest/distancedistancematrixdescriptors.py
PyL3dMDTest/geary.py
PyL3dMDTest/geometricdescriptors.py
PyL3dMDTest/getadjacencyanddistancematrices.py
PyL3dMDTest/getatomicproperties.py
PyL3dMDTest/getaway.py
PyL3dMDTest/getinfofromlammpsdatafile.py
PyL3dMDTest/getinfofromlammpstrajfile.py
PyL3dMDTest/moran.py
PyL3dMDTest/moreaubroto.py
PyL3dMDTest/morse.py
PyL3dMDTest/rdf.py
PyL3dMDTest/removehydrogenfrommolecule.py
PyL3dMDTest/topologyconnectivity3Ddescriptors.py
PyL3dMDTest/whim.py
PyL3dMDTest-0.0.23.dist-info/METADATA
PyL3dMDTest-0.0.23.dist-info/WHEEL
PyL3dMDTest-0.0.23.dist-info/top_level.txt
PyL3dMDTest-0.0.23.dist-info/RECORD
