Metadata-Version: 2.1
Name: PyL3dMDTest
Version: 0.0.23
Summary: Python LAMMPS 3-Dimensional Molecular Dynamics/Descriptors
Author: Pawan Panwar, Quanpeng Yang, Ashlie Martini
Author-email: samtari@163.com
License: UNKNOWN
Keywords: Python,LAMMPS,Molecular Dynamics Simulations,Descriptors,Machine Learning,MD Simulations,3-Dimensional
Platform: UNKNOWN
Classifier: Development Status :: 3 - Alpha
Classifier: Intended Audience :: Education
Classifier: Programming Language :: Python :: 2
Classifier: Programming Language :: Python :: 3
Classifier: Operating System :: MacOS :: MacOS X
Classifier: Operating System :: Microsoft :: Windows
